AUTHORS.rst
CONTRIBUTING.rst
HISTORY.rst
LICENSE
MANIFEST.in
README.rst
requirements.txt
setup.cfg
setup.py
docs/Makefile
docs/authors.rst
docs/conf.py
docs/contributing.rst
docs/history.rst
docs/index.rst
docs/installation.rst
docs/make.bat
docs/readme.rst
docs/usage.rst
geehydro/__init__.py
geehydro/add_layer.py
geehydro/basemaps.py
geehydro/cli.py
geehydro/geehydro.py
geehydro/utilities.py
geehydro.egg-info/PKG-INFO
geehydro.egg-info/SOURCES.txt
geehydro.egg-info/dependency_links.txt
geehydro.egg-info/entry_points.txt
geehydro.egg-info/not-zip-safe
geehydro.egg-info/requires.txt
geehydro.egg-info/top_level.txt
tests/__init__.py
tests/test_geehydro.py