Metadata-Version: 1.2
Name: geehydro
Version: 0.1.4
Summary: Python package for mapping inundation dynamics using Google Earth Engine
Home-page: https://github.com/giswqs/geehydro
Author: Qiusheng Wu
Author-email: giswqs@gmail.com
License: MIT license
Keywords: geehydro
Platform: UNKNOWN
Classifier: Development Status :: 2 - Pre-Alpha
Classifier: Intended Audience :: Developers
Classifier: License :: OSI Approved :: MIT License
Classifier: Natural Language :: English
Classifier: Programming Language :: Python :: 2
Classifier: Programming Language :: Python :: 2.7
Classifier: Programming Language :: Python :: 3
Classifier: Programming Language :: Python :: 3.5
Classifier: Programming Language :: Python :: 3.6
Classifier: Programming Language :: Python :: 3.7
Classifier: Programming Language :: Python :: 3.8
Requires-Python: >=2.7, !=3.0.*, !=3.1.*, !=3.2.*, !=3.3.*, !=3.4.*
